{"title": "\u53d6\u6570\u4ef7\u503c", "type": "problem", "description": {"format": "html", "value": "\u7ed9\u51fa\u957f\u5ea6\u4e3aN\u7684\u6570\u5217{A_i}\uff0c\u6bcf\u6b21\u53ef\u4ee5\u4ece\u6700\u5de6\u8fb9\u6216\u8005\u6700\u53f3\u8fb9\u53d6\u8d70\u4e00\u4e2a\u6570\uff0c\u7b2ci\u6b21\u53d6\u6570\u5f97\u5230\u7684\u4ef7\u503c\u662fi&nbsp; *&nbsp; A_j\u3002\u6c42\u4ef7\u503c\u4e4b\u548c\u6700\u5927\u7684\u53d6\u6570\u65b9\u6848\u3002\n"}, "tags": ["TYVJ"], "input_description": {"format": "html", "value": "&nbsp; &nbsp; &nbsp; &nbsp; \u7b2c\u4e00\u884c\uff0c\u4e00\u4e2a\u6574\u6570\uff0c\u8868\u793a\u6570\u5217\u957f\u5ea6N\u3002\n&nbsp; &nbsp; &nbsp; &nbsp; \u63a5\u4e0b\u6765N\u884c\uff0c\u6bcf\u884c\u4e00\u4e2a\u6574\u6570\uff0c\u8868\u793a\u6570\u5217A_i\u3002\n"}, "output_description": {"format": "html", "value": "\u4e00\u4e2a\u6574\u6570\uff0c\u8868\u793a\u6700\u5927\u7684\u4ef7\u503c\u4e4b\u548c\u3002\n"}, "test_case_score": [{"score": 10, "input_name": "1.in", "output_name": "1.out"}, {"score": 10, "input_name": "2.in", "output_name": "2.out"}, {"score": 10, "input_name": "3.in", "output_name": "3.out"}, {"score": 10, "input_name": "4.in", "output_name": "4.out"}, {"score": 10, "input_name": "5.in", "output_name": "5.out"}, {"score": 10, "input_name": "6.in", "output_name": "6.out"}, {"score": 10, "input_name": "7.in", "output_name": "7.out"}, {"score": 10, "input_name": "8.in", "output_name": "8.out"}, {"score": 10, "input_name": "9.in", "output_name": "9.out"}, {"score": 10, "input_name": "10.in", "output_name": "10.out"}], "hint": {"format": "html", "value": "N&nbsp; &lt; =&nbsp; 2000&nbsp; ,&nbsp; A_i&nbsp; &lt; =&nbsp; 1000\n"}, "time_limit": 1000, "memory_limit": 128, "samples": [{"input": "5\n1\n3\n1\n5\n2\n", "output": "43\n"}], "template": {}, "spj": null, "rule_type": "OI", "source": "", "answers": [{"language": "Python3", "code": "print('Hello, world!')"}]}