{"title": "\u9ad8\u7cbe\u5ea6\u9636\u4e58\u7684\u548c", "type": "problem", "description": {"format": "html", "value": "<p class=\"MsoList\" style=\"margin-left:15.75pt;text-indent:-15.75pt;\">\n\t\u7528\u9ad8\u7cbe\u5ea6\u8ba1\u7b97\u51fa<span>S=1!</span><span>+2!</span><span>+3!</span><span>+</span>\u2026<span>+N!</span>\uff08<span>N</span>\u2264<span>50</span>\uff09\uff0c<span style=\"line-height:1.5;\">\u5176\u4e2d\"!\"\u8868\u793a\u9636\u4e58\uff0c\u4f8b\u5982\uff1a</span><span style=\"line-height:1.5;\">5!</span><span style=\"line-height:1.5;\">=5*4*3*2*1</span><span style=\"line-height:1.5;\">\u3002</span> \n</p>\n<p class=\"MsoList\" style=\"margin-left:15.75pt;text-indent:-15.75pt;\">\n\t<span></span> \n</p>\n<p>\n\t\u8f93\u5165\u6b63\u6574\u6570N\uff0c\u8f93\u51fa\u8ba1\u7b97\u7ed3\u679cS\u3002\n</p>\n<p>\n\t<br />\n</p>"}, "tags": ["NOIP\u5168\u56fd\u8054\u8d5b\u666e\u53ca\u7ec4", "1998\u5e74NOIP\u5168\u56fd\u8054\u8d5b\u666e\u53ca\u7ec4"], "input_description": {"format": "html", "value": "<p>\n\t\u6bcf\u4e2a\u6d4b\u8bd5\u6587\u4ef6\u53ea\u5305\u542b\u4e00\u7ec4\u6d4b\u8bd5\u6570\u636e\uff0c\u6bcf\u7ec4\u8f93\u5165\u4e00\u4e2a\u6b63\u6574\u6570N\u3002\n</p>\n<p>\n\t<br />\n</p>"}, "output_description": {"format": "html", "value": "<p>\n\t\u5bf9\u4e8e\u6bcf\u7ec4\u8f93\u5165\u6570\u636e\uff0c\u8f93\u51fa\u9636\u4e58\u548c\u7684\u8ba1\u7b97\u7ed3\u679c\u3002\n</p>\n<p>\n\t<br />\n</p>"}, "test_case_score": [{"score": 10, "input_name": "factor1.in", "output_name": "factor1.out"}, {"score": 10, "input_name": "factor4.in", "output_name": "factor4.out"}, {"score": 10, "input_name": "factor2.in", "output_name": "factor2.out"}, {"score": 10, "input_name": "factor3.in", "output_name": "factor3.out"}], "hint": {"format": "html", "value": ""}, "time_limit": 1000, "memory_limit": 125, "samples": [{"input": "3", "output": "9"}], "template": {}, "spj": null, "rule_type": "OI", "source": "", "answers": [{"language": "Python3", "code": "print('Hello, world!')"}]}