{"read": [{"type": "\u7287\u7287\u70b9\u8d5e", "time": 1643446351.1793346, "msg": "{\"user\": \"diyanqi\", \"msg\": \"<a href=\\\"/user/1\\\">diyanqi</a> \\u8d5e\\u4e86\\u4f60\\u7684\\u7287\\u7287>>\"}", "link": "/chat/33"}, {"type": "\u7287\u7287\u56de\u590d", "time": 1643446347.0238447, "msg": "{\"user\": \"diyanqi\", \"msg\": \"<a href=\\\"/user/1\\\">diyanqi</a> \\u56de\\u590d\\u4e86\\u4f60\\u7684\\u7287\\u7287>>\"}", "link": "/chat/33"}, {"type": "\u7287\u7287\u56de\u590d", "time": 1643292437.6319022, "msg": "{\"user\": \"diyanqi\", \"msg\": \"<a href=\\\"/user/1\\\">diyanqi</a> \\u56de\\u590d\\u4e86\\u4f60\\u7684\\u7287\\u7287>>\"}", "link": "/chat/31"}, {"type": "\u56de\u7b54", "time": 1643250897.1567347, "msg": "{\"user\": \"diyanqi\", \"msg\": \"<a href=\\\"/user/1\\\">diyanqi</a> \\u89e3\\u7b54\\u4e86\\u4f60\\u7684\\u7591\\u60d1>>\"}", "link": "/ask/3"}, {"type": "\u540c\u95ee", "time": 1643244829.3761415, "msg": "{\"user\": \"diyanqi\", \"msg\": \"<a href=\\\"/user/1\\\">diyanqi</a> \\u548c\\u4f60\\u6709\\u540c\\u6837\\u7684\\u7591\\u60d1>>\"}", "link": "/ask/3"}, {"type": "\u7287\u7287\u70b9\u8d5e", "time": 1643205996.9724436, "msg": "{\"user\": \"diyanqi\", \"msg\": \"<a href=\\\"/user/1\\\">diyanqi</a> \\u8d5e\\u4e86\\u4f60\\u7684\\u7287\\u7287>>\"}", "link": "/chat/28"}, {"type": "\u7287\u7287\u56de\u590d", "time": 1643205993.9435654, "msg": "{\"user\": \"diyanqi\", \"msg\": \"<a href=\\\"/user/1\\\">diyanqi</a> \\u56de\\u590d\\u4e86\\u4f60\\u7684\\u7287\\u7287>>\"}", "link": "/chat/28"}, {"type": "\u5173\u6ce8", "time": 1643182606.5251312, "msg": "{\"user\": \"\\u8def\\u4eba\", \"msg\": \"<a href=\\\"/user/6\\\">\\u8def\\u4eba</a> \\u5173\\u6ce8\\u4e86\\u4f60\"}", "link": "/user/6"}, {"type": "\u56de\u7b54", "time": 1643182539.7423995, "msg": "{\"user\": \"\\u8def\\u4eba\", \"msg\": \"<a href=\\\"/user/6\\\">\\u8def\\u4eba</a> \\u89e3\\u7b54\\u4e86\\u4f60\\u7684\\u7591\\u60d1>>\"}", "link": "/ask/3"}, {"type": "\u5173\u6ce8", "time": 1643099548.2502618, "msg": "{\"user\": \"tobylai\", \"msg\": \"<a href=\\\"/user/3\\\">tobylai</a> \\u5173\\u6ce8\\u4e86\\u4f60\"}", "link": "/user/6"}, {"type": "\u7287\u7287\u70b9\u8d5e", "time": 1642914178.1130624, "msg": "{\"user\": \"diyanqi\", \"msg\": \"<a href=\\\"/user/1\\\">diyanqi</a> \\u8d5e\\u4e86\\u4f60\\u7684\\u7287\\u7287>>\"}", "link": "/chat/17"}, {"type": "\u5173\u6ce8", "time": 1642910975.7480297, "msg": "{\"user\": \"diyanqi\", \"msg\": \"<a href=\\\"/user/1\\\">diyanqi</a> \\u5173\\u6ce8\\u4e86\\u4f60\"}", "link": "/user/6"}, {"type": "\u7287\u7287\u70b9\u8d5e", "time": 1642828629.1398613, "msg": "\u6709\u4eba\u8d5e\u4e86\u4f60\u7684\u7287\u7287>>", "link": "/chat/17"}, {"type": "\u7287\u7287\u56de\u590d", "time": 1642828625.6346483, "msg": "\u6709\u4eba\u56de\u590d\u4e86\u4f60\u7684\u7287\u7287>>", "link": "/chat/17"}], "unread": [{"type": "\u7287\u7287\u56de\u590d", "time": 1643623220.708319, "msg": "{\"user\": \"tobylai\", \"msg\": \"<a href=\\\"/user/3\\\">tobylai</a> \\u56de\\u590d\\u4e86\\u4f60\\u7684\\u7287\\u7287>>\"}", "link": "/chat/30"}]}