{"title": " [ZJOI2010]\u7f51\u7edc\u6269\u5bb9", "type": "problem", "description": {"format": "html", "value": "<p>\n\t\u7ed9\u5b9a\u4e00\u5f20\u6709\u5411\u56fe\uff0c\u6bcf\u6761\u8fb9\u90fd\u6709\u4e00\u4e2a\u5bb9\u91cfC\u548c\u4e00\u4e2a\u6269\u5bb9\u8d39\u7528W\u3002\u8fd9\u91cc\u6269\u5bb9\u8d39\u7528\u662f\u6307\u5c06\u5bb9\u91cf\u6269\u59271\u6240\u9700\u7684\u8d39\u7528\u3002\u6c42\uff1a 1\u3001 \u5728\u4e0d\u6269\u5bb9\u7684\u60c5\u51b5\u4e0b\uff0c1\u5230N\u7684\u6700\u5927\u6d41\uff1b 2\u3001 \u5c061\u5230N\u7684\u6700\u5927\u6d41\u589e\u52a0K\u6240\u9700\u7684\u6700\u5c0f\u6269\u5bb9\u8d39\u7528\u3002\n</p>\n<h2>\n\t\u8f93\u5165\u8f93\u51fa\u683c\u5f0f\n</h2>\n<strong>\u8f93\u5165\u683c\u5f0f\uff1a</strong><br />\n<p>\n\t<br />\n</p>\n<p>\n\t\u8f93\u5165\u6587\u4ef6\u7684\u7b2c\u4e00\u884c\u5305\u542b\u4e09\u4e2a\u6574\u6570N,M,K\uff0c\u8868\u793a\u6709\u5411\u56fe\u7684\u70b9\u6570\u3001\u8fb9\u6570\u4ee5\u53ca\u6240\u9700\u8981\u589e\u52a0\u7684\u6d41\u91cf\u3002 \u63a5\u4e0b\u6765\u7684M\u884c\u6bcf\u884c\u5305\u542b\u56db\u4e2a\u6574\u6570u,v,C,W\uff0c\u8868\u793a\u4e00\u6761\u4eceu\u5230v\uff0c\u5bb9\u91cf\u4e3aC\uff0c\u6269\u5bb9\u8d39\u7528\u4e3aW\u7684\u8fb9\u3002\n</p>\n<p>\n\t<br />\n</p>\n<strong>\u8f93\u51fa\u683c\u5f0f\uff1a</strong><br />\n<p>\n\t<br />\n</p>\n<p>\n\t\u8f93\u51fa\u6587\u4ef6\u4e00\u884c\u5305\u542b\u4e24\u4e2a\u6574\u6570\uff0c\u5206\u522b\u8868\u793a\u95ee\u98981\u548c\u95ee\u98982\u7684\u7b54\u6848\u3002\n</p>\n<p>\n\t<br />\n</p>\n<h2>\n\t\u8f93\u5165\u8f93\u51fa\u6837\u4f8b\n</h2>\n<div class=\"am-g\">\n\t<div class=\"am-u-md-6 copy-region\">\n\t\t<strong>\u8f93\u5165\u6837\u4f8b#1\uff1a</strong> <a class=\"am-badge am-radius lg-bg-orange sample-copy\">\u590d\u5236</a> \n<pre>5 8 2\n1 2 5 8\n2 5 9 9\n5 1 6 2\n5 1 1 8\n1 2 8 7\n2 5 4 9\n1 2 1 1\n1 4 2 1</pre>\n\t</div>\n\t<div class=\"am-u-md-6 copy-region\">\n\t\t<strong>\u8f93\u51fa\u6837\u4f8b#1\uff1a</strong> <a class=\"am-badge am-radius lg-bg-orange sample-copy\">\u590d\u5236</a> \n<pre>13 19\n</pre>\n\t</div>\n</div>\n<h2>\n\t\u8bf4\u660e\n</h2>\n<p>\n\t30%\u7684\u6570\u636e\u4e2d\uff0cN&lt;=100\n</p>\n<p>\n\t100%\u7684\u6570\u636e\u4e2d\uff0cN&lt;=1000\uff0cM&lt;=5000\uff0cK&lt;=10\n</p>\n<div class=\"lg-article-sub am-g\" id=\"sub\">\n</div>"}, "tags": ["ZJOI2010", "ZJOI", "\u7701\u9009", "\u9ad8\u7ea7"], "input_description": {"format": "html", "value": ""}, "output_description": {"format": "html", "value": ""}, "test_case_score": [{"score": 10, "input_name": "test7.in", "output_name": "test7.out"}, {"score": 10, "input_name": "test2.in", "output_name": "test2.out"}, {"score": 10, "input_name": "test9.in", "output_name": "test9.out"}, {"score": 10, "input_name": "test0.in", "output_name": "test0.out"}, {"score": 10, "input_name": "test1.in", "output_name": "test1.out"}, {"score": 10, "input_name": "test3.in", "output_name": "test3.out"}, {"score": 10, "input_name": "test5.in", "output_name": "test5.out"}, {"score": 10, "input_name": "test6.in", "output_name": "test6.out"}, {"score": 10, "input_name": "test8.in", "output_name": "test8.out"}, {"score": 10, "input_name": "test4.in", "output_name": "test4.out"}], "hint": {"format": "html", "value": ""}, "time_limit": 1000, "memory_limit": 128, "samples": [{"input": "", "output": ""}], "template": {}, "spj": null, "rule_type": "OI", "source": "", "answers": [{"language": "Python3", "code": "print('Hello, world!')"}]}